<?xml version="1.0" encoding="utf-8"?>
<resources>
    <string name="JOHN/Arvo_Greeting 0_Intro_000">Schon Nachmittag , was, &lt;PlayerName&gt; ?</string>
    <string name="JOHN/RandomConvo_024_Option_001">Sicher!</string>
    <string name="JOHN/Low_Friendship_Greeting 0_Intro_000">Guten Tag &lt;PlayerName&gt;.</string>
    <string name="JOHN/SkyFest_Morning_001_Intro_000">Guten Tag &lt;PlayerName&gt;.</string>
    <string name="JOHN/Arvo_Greeting 0_Response_003_000">&lt;yes&gt;Also gut, nette Unterhaltung.</string>
    <string name="JOHN/Medium_Friendship_Greeting 0_Intro_001">Was ist los?</string>
    <string name="JOHN/Medium_Friendship_Greeting 1_Intro_000">&lt;PlayerName&gt;!</string>
    <string name="JOHN/SkyFest_AfterNoon_001_Intro_000">Richtig.</string>
    <string name="JOHN/SkyFest_Night_001_Intro_000">Wow!</string>
    <string name="JOHN/High_Friendship_Greeting 1_Intro_001">Brauchst du etwas?</string>
    <string name="JOHN/Highest_Friendship_Greeting 1_Intro_000">Ah, &lt;PlayerName&gt;!</string>
    <string name="JOHN/Low_Friendship_Greeting 2_Intro_001">Brauchst du etwas?</string>
    <string name="JOHN/Wind_Greeting 1_Intro_000">Ah, &lt;PlayerName&gt;!</string>
    <string name="JOHN/Cold_Greeting 1_Intro_000">Oh, guten Tag &lt;PlayerName&gt;.</string>
</resources>