<?xml version="1.0" encoding="utf-8"?>
<resources>
    <string name="ToolTips/AskForJob_0">Kann ich etwas für dich erledigen?</string>
    <string name="ToolTips/Tip_Cancel">Abbrechen</string>
    <string name="ToolTips/Tip_PlaceDeed">Plazieren</string>
    <string name="ToolTips/Sell">Verkaufen</string>
    <string name="ToolTips/AskForJob_1">Brauchst du etwas?</string>
    <string name="ToolTips/CompleteBoardRequest_0">Ich habe deine Anfrage abgeschlossen!</string>
    <string name="ToolTips/AskToChat_2">Lass uns reden!</string>
    <string name="ToolTips/AskToChat_3">Was ist los?</string>
    <string name="ToolTips/AskToHangOut_0">Lass uns abhängen!</string>
    <string name="ToolTips/AskToChat_0">Lass uns reden!</string>
    <string name="ToolTips/AskToChat_1">Was gibt\'s Neues?</string>
    <string name="ToolTips/CompleteBoardRequest_1">Ich habe das für dich getan!</string>
    <string name="ToolTips/GiveItem_0">Hier ist es!</string>
    <string name="ToolTips/Catch">Fangen</string>
    <string name="ToolTips/AskToHangOut_1">Willst du abhängen?</string>
    <string name="ToolTips/AskToHangOut_2">Willst du abhängen?</string>
    <string name="ToolTips/CancelConvo_0">Vergiss es</string>
    <string name="ToolTips/CancelConvo_1">Bis später</string>
    <string name="ToolTips/CancelConvo_2">Tschüss!</string>
    <string name="ToolTips/CancelConvo_3">Ich fange dich.</string>
    <string name="ToolTips/CustomiseHouse">Haus anpassen</string>
    <string name="ToolTips/PlaceOne">Eins platzieren</string>
    <string name="ToolTips/Hover_Increasesloggingdamage">Erhöht den Schaden beim Holzfällen</string>
    <string name="ToolTips/Hover_Increasesmovementspeed">Erhöht die Bewegungsgeschwindigkeit</string>
    <string name="ToolTips/Found" resizable="True">Gefunden</string>
    <string name="ToolTips/Hover_Increasesreelinspeed">Erhöht die Geschwindigkeit beim Einholen</string>
    <string name="ToolTips/Hover_HealthTickspeedisincreasedforfasterhealthregen">Die Geschwindigkeit des Lebenspunkte-Ticks wurde erhöht, um die Lebenspunkte schneller wiederherzustellen</string>
    <string name="ToolTips/Release">Freigeben</string>
    <string name="ToolTips/Tip_ShopClosed">Laden geschlossen</string>
    <string name="ToolTips/Tip_Sit">Sitz</string>
    <string name="ToolTips/Tip_StopDriving">Fahrverbot</string>
    <string name="ToolTips/Spin">Drehen</string>
    <string name="ToolTips/Write">Schreibe</string>
    <string name="ToolTips/Switch">Schalter</string>
    <string name="ToolTips/Boost">Boost</string>
    <string name="ToolTips/SwapBlade">Klinge tauschen</string>
    <string name="ToolTips/SelectAmount">Betrag auswählen</string>
    <string name="ToolTips/SplitStack">Stapel teilen</string>
    <string name="ToolTips/Hover_HuntingBuff">Jagen Stärkung</string>
    <string name="ToolTips/Hover_StaminaRegen">Ausdauer Regeneration</string>
    <string name="ToolTips/Hover_Increasesexperience">Erhöht die Erfahrung</string>
    <string name="ToolTips/HideHUD">Hud ausblenden</string>
    <string name="ToolTips/Hover_AutoStackfromPockets">Automatischer stapeln aus Taschen</string>
    <string name="ToolTips/Hover_LoggingBuff">Holzfäller Stärkung</string>
    <string name="ToolTips/Hover_Increasesweapondamage">Erhöht den Waffenschaden</string>
    <string name="ToolTips/Hover_Staminarecoveredpersecond">Wiederhergestellte Ausdauer pro Sekunde</string>
    <string name="ToolTips/Hover_Sleepless">Schlaflos</string>
    <string name="ToolTips/Hover_Ignorestireddebuff">Ignoriert die Müdigkeitsschwächung</string>
    <string name="ToolTips/Hover_ExperienceBuff">Erfahrungs-Stärkung</string>
    <string name="ToolTips/Hover_Powertoolswontconsumedurability">Elektrowerkzeuge verbrauchen keine Haltbarkeit</string>
    <string name="ToolTips/Hover_MiningBuff">Bergbau Stärkung</string>
    <string name="ToolTips/Hover_Increasesminingdamage">Erhöht den Schaden durch Bergbau</string>
    <string name="ToolTips/Hover_WellRested">Gut ausgeruht</string>
    <string name="ToolTips/GiveItem_1">Das ist für dich!</string>
    <string name="ToolTips/Tip_Buy">Kaufen</string>
    <string name="ToolTips/Tip_ClerkBusy">Sachbearbeiter Beschäftigt</string>
    <string name="ToolTips/Tip_Close">Schließen</string>
    <string name="ToolTips/Tip_Drive">Fahren</string>
    <string name="ToolTips/Tip_Drop">Fallen</string>
    <string name="ToolTips/Tip_GetUp">Aufstehen</string>
    <string name="ToolTips/Tip_Harvest">Ernte</string>
    <string name="ToolTips/Tip_Insert">einfügen</string>
    <string name="ToolTips/Tip_IsBusy">ist beschäftigt</string>
    <string name="ToolTips/Tip_LayDown">Hinlegen</string>
    <string name="ToolTips/Tip_Open">Öffnen</string>
    <string name="ToolTips/Tip_Pet">Haustier</string>
    <string name="ToolTips/Tip_PickUp">Abholen</string>
    <string name="ToolTips/Tip_TalkTo">Sprich mit</string>
    <string name="ToolTips/Craft">Handwerk</string>
    <string name="ToolTips/Use">Verwende</string>
    <string name="ToolTips/Plant">Pflanze</string>
    <string name="ToolTips/Water">Gieße</string>
    <string name="ToolTips/Cook">Koch</string>
    <string name="ToolTips/Hover_Fullness">Fülle</string>
    <string name="ToolTips/Tip_PocketsFull">Taschen voll</string>
    <string name="ToolTips/Tip_Read">Lesen</string>
    <string name="ToolTips/Tip_Requires">Erfordert</string>
    <string name="ToolTips/Tip_Rotate">Drehen</string>
    <string name="ToolTips/Smash">Zerstöre</string>
    <string name="ToolTips/Grind">Mahle</string>
    <string name="ToolTips/CutDown">Abschneiden</string>
    <string name="ToolTips/Buy">Kaufen</string>
    <string name="ToolTips/Hunt">Jagen</string>
    <string name="ToolTips/Clear">Entferne</string>
    <string name="ToolTips/Saw">Säge</string>
    <string name="ToolTips/ReelIn">Einholen</string>
    <string name="ToolTips/Hover_Slightstaminarecoveryforagoodnightsrest">Leichte Erholung der Ausdauer für eine erholsame Nachtruhe</string>
    <string name="ToolTips/Hover_Diligent">Fleißig</string>
    <string name="ToolTips/Hover_Toolsandweaponswontconsumedurability">Werkzeuge und Waffen verbrauchen keine Haltbarkeit</string>
    <string name="ToolTips/Hover_Sickness">Krankheit</string>
    <string name="ToolTips/Hover_Staminawontrecover">Die Ausdauer erholt sich nicht</string>
    <string name="ToolTips/Hover_FishingBuff">Angler Stärkung</string>
    <string name="ToolTips/Hover_FastHealthTickSpeed">Schnelles Gesundheitstick-Tempo</string>
    <string name="ToolTips/Hover_DefenceBuff">Verteidigungs-Stärkung</string>
    <string name="ToolTips/Hover_SwimmingBuff">Schwimm Stärkung</string>
    <string name="ToolTips/Hover_FarmingBuff">Landwirtschaft Stärkung</string>
    <string name="ToolTips/Hover_Increasesfarming?">Landwirtschaft erhöhen?</string>
    <string name="ToolTips/Hover_Increasesswimmingspeed">Erhöht die Schwimmgeschwindigkeit</string>
    <string name="ToolTips/Hover_HealthRegen">Gesundheit Regeneration</string>
    <string name="ToolTips/Hover_Healthrecoveredper20sec">Wiederhergestellte Gesundheit pro 20 Sekunden</string>
    <string name="ToolTips/Hover_Decreasesdamagetaken">Verringert den erlittenen Schaden</string>
    <string name="ToolTips/Hover_SpeedBuff">Schnelligkeits-Stärkung</string>
    <string name="ToolTips/Hover_Sitting">Sitzen</string>
    <string name="ToolTips/Hover_Increaseshealthrecoveryspeed">Erhöht die Geschwindigkeit der Gesundheitserholung</string>
    <string name="ToolTips/UseCamera">Kamera verwenden</string>
    <string name="ToolTips/Check">Prüfe</string>
    <string name="ToolTips/Insert">einfügen</string>
    <string name="ToolTips/Full">Voll</string>
    <string name="ToolTips/Dive">Tauchen</string>
    <string name="ToolTips/QuickMove">Schnelle Bewegung</string>
    <string name="ToolTips/StackAll">Alle stapeln</string>
    <string name="ToolTips/Hover_Charged">Aufgeladen</string>
</resources>